u/__init__.py
u/__main__.py
u/_utils.py
u/capital_quantities.py
u/prefixes.py
u/quantity.py
u/unit.py
u/cli/__init__.py
u/cli/make_derived_quantity.py
u/quantities/__init__.py
u/quantities/acceleration.py
u/quantities/amount_of_substance.py
u/quantities/angle.py
u/quantities/area.py
u/quantities/data_transfer_speed.py
u/quantities/data_volume.py
u/quantities/distance.py
u/quantities/duration.py
u/quantities/electric_charge.py
u/quantities/electric_current.py
u/quantities/electric_resistance.py
u/quantities/force.py
u/quantities/frequency.py
u/quantities/luminous_intensity.py
u/quantities/mass.py
u/quantities/one.py
u/quantities/pixels.py
u/quantities/solid_angle.py
u/quantities/speed.py
u/quantities/temperature.py
u-1.0.3.dist-info/WHEEL
u-1.0.3.dist-info/METADATA
u-1.0.3.dist-info/RECORD
