Metadata-Version: 2.3
Name: u
Version: 1.0.3
Summary: Statically typed units
Author-email: Aran-Fey <rawing7@gmail.com>
Requires-Python: >= 3.9.2
Requires-Dist: typing-extensions
Requires-Dist: revel>=0.9.0
